aoc/__init__.py
aoc/__main__.py
aoc/constants.py
aoc/data.py
aoc/errors.py
aoc/ext/__init__.py
aoc/ext/constants.py
aoc/ext/splits.py
aoc/http.py
aoc/main.py
aoc/names.py
aoc/primitives.py
aoc/runners.py
aoc/solutions.py
aoc/states.py
aoc/time.py
aoc/timers.py
aoc/tokens.py
aoc/versions.py
aoc_core-0.2.0.dist-info/LICENSE
aoc_core-0.2.0.dist-info/METADATA
aoc_core-0.2.0.dist-info/WHEEL
aoc_core-0.2.0.dist-info/entry_points.txt
aoc_core-0.2.0.dist-info/RECORD
