Metadata-Version: 2.1
Name: aoc-core
Version: 0.2.0
Summary: Advent of Code in Python.
Home-page: https://github.com/nekitdev/aoc-core
License: MIT
Keywords: python,aoc
Author: nekitdev
Requires-Python: >=3.8
Classifier: Development Status :: 4 - Beta
Classifier: Intended Audience :: Developers
Classifier: License :: OSI Approved :: MIT License
Classifier: Operating System :: OS Independent
Classifier: Programming Language :: Python :: 3
Classifier: Programming Language :: Python :: 3.8
Classifier: Programming Language :: Python :: 3.9
Classifier: Programming Language :: Python :: 3.10
Classifier: Programming Language :: Python :: 3.11
Classifier: Programming Language :: Python :: 3.12
Classifier: Topic :: Utilities
Classifier: Typing :: Typed
Provides-Extra: ext
Requires-Dist: aiohttp (>=3.9.5)
Requires-Dist: attrs (>=23.2.0)
Requires-Dist: click (>=8.1.7)
Requires-Dist: entrypoint (>=2.0.3)
Requires-Dist: funcs (>=0.10.1) ; extra == "ext"
Requires-Dist: iters (>=0.18.0) ; extra == "ext"
Requires-Dist: pendulum (>=3.0.0)
Requires-Dist: trogon (>=0.5.0) ; python_version >= "3.8" and python_version < "4.0"
Requires-Dist: typing-aliases (>=1.10.1)
Requires-Dist: typing-extensions (>=4.11.0)
Requires-Dist: versions (>=3.0.0)
Requires-Dist: wraps (>=0.10.0)
Requires-Dist: yarl (>=1.9.4)
Project-URL: Chat, https://nekit.dev/chat
Project-URL: Documentation, https://nekitdev.github.io/aoc-core
Project-URL: Funding, https://nekit.dev/funding
Project-URL: Issues, https://github.com/nekitdev/aoc-core/issues
Project-URL: Repository, https://github.com/nekitdev/aoc-core
